Metadata-Version: 2.1
Name: climetlab-maelstrom-ens10
Version: 0.1.1
Summary: A dataset plugin for climetlab for the ENS10 MAELSTROM dataset.
Home-page: https://github.com/spcl/climetlab-maelstrom-ens10
Author: SPCL @ ETH Zurich
Author-email: talbn@inf.ethz.ch
License: Apache License Version 2.0
Keywords: meteorology
Platform: UNKNOWN
Classifier: Development Status :: 3 - Alpha
Classifier: Intended Audience :: Developers
Classifier: License :: OSI Approved :: Apache Software License
Classifier: Programming Language :: Python :: 3
Classifier: Programming Language :: Python :: 3.6
Classifier: Programming Language :: Python :: 3.7
Classifier: Programming Language :: Python :: 3.8
Classifier: Programming Language :: Python :: 3.9
Classifier: Programming Language :: Python :: Implementation :: CPython
Classifier: Programming Language :: Python :: Implementation :: PyPy
Classifier: Operating System :: OS Independent
License-File: LICENSE
